docker_events-0.0.10.dist-info/top_level.txt
docker_events-0.0.10.dist-info/entry_points.txt
docker_events-0.0.10.dist-info/METADATA
docker_events-0.0.10.dist-info/DESCRIPTION.rst
docker_events-0.0.10.dist-info/namespace_packages.txt
docker_events-0.0.10.dist-info/WHEEL
docker_events-0.0.10.dist-info/metadata.json
docker_events-0.0.10.dist-info/RECORD
docker_events/scripts.py
docker_events/__init__.py
docker_events/tools.py
docker_events/tools/skydns.py
docker_events/tools/__init__.py
